FWHFDL/BBO.py
FWHFDL/DE.py
FWHFDL/FireFly.py
FWHFDL/HS.py
FWHFDL/IWO.py
FWHFDL/PSO.py
FWHFDL/SA.py
FWHFDL/TLBO.py
FWHFDL/__init__.py
FWHFDL/check_bound.py
FWHFDL/cost_function.py
FWHFDL/problem_types.py
fwhfdl-0.0.2.dist-info/METADATA
fwhfdl-0.0.2.dist-info/WHEEL
fwhfdl-0.0.2.dist-info/licenses/LICENSE
fwhfdl-0.0.2.dist-info/RECORD
