Metadata-Version: 2.4
Name: FWHFDL
Version: 0.0.2
Summary: WHFDL Feature Selector
Project-URL: source, https://github.com/arman-daliri/WHFDL
Author-email: Arman Daliri <daliriwork2@gmail.com>
Maintainer-email: Mohammad Mahdi Mir <standardret@proton.me>
License-Expression: MIT
License-File: LICENSE
Classifier: Intended Audience :: Science/Research
Classifier: Operating System :: OS Independent
Classifier: Programming Language :: Python
Classifier: Programming Language :: Python :: 3
Requires-Python: >=3.11
Requires-Dist: numpy
Requires-Dist: scikit-learn
